netneurotools/__init__.py
netneurotools/_version.py
netneurotools/civet.py
netneurotools/cluster.py
netneurotools/colors.py
netneurotools/freesurfer.py
netneurotools/metrics.py
netneurotools/modularity.py
netneurotools/networks.py
netneurotools/plotting.py
netneurotools/stats.py
netneurotools/surface.py
netneurotools/utils.py
netneurotools/data/osf.json
netneurotools/datasets/__init__.py
netneurotools/datasets/fetchers.py
netneurotools/datasets/generators.py
netneurotools/datasets/mirchi.py
netneurotools/datasets/utils.py
netneurotools/tests/__init__.py
netneurotools/tests/test_civet.py
netneurotools/tests/test_cluster.py
netneurotools/tests/test_datasets.py
netneurotools/tests/test_freesurfer.py
netneurotools/tests/test_metrics.py
netneurotools/tests/test_modularity.py
netneurotools/tests/test_plotting.py
netneurotools/tests/test_stats.py
netneurotools/tests/test_utils.py
netneurotools_scipyfix-0.0.0.dist-info/LICENSE
netneurotools_scipyfix-0.0.0.dist-info/METADATA
netneurotools_scipyfix-0.0.0.dist-info/WHEEL
netneurotools_scipyfix-0.0.0.dist-info/top_level.txt
netneurotools_scipyfix-0.0.0.dist-info/RECORD
