Metadata-Version: 2.1
Name: netneurotools-scipyfix
Version: 0.0.0
Summary: Commonly used tools in the Network Neuroscience Lab
Home-page: https://github.com/netneurolab/netneurotools
Download-URL: https://github.com/netneurolab/netneurotools
Author: netneurotools developers
Author-email: rossmarkello+coding@gmail.com
Maintainer: Network Neuroscience Lab
Maintainer-email: rossmarkello+coding@gmail.com
License: BSD-3
Platform: OS Independent
Classifier: Development Status :: 3 - Alpha
Classifier: Intended Audience :: Science/Research
Classifier: License :: OSI Approved :: BSD License
Classifier: Programming Language :: Python :: 3.6
Classifier: Programming Language :: Python :: 3.7
Classifier: Programming Language :: Python :: 3.8
Provides: netneurotools
Requires-Python: >=3.6
License-File: LICENSE
Requires-Dist: bctpy
Requires-Dist: matplotlib
Requires-Dist: nibabel
Requires-Dist: nilearn
Requires-Dist: numpy >=1.16
Requires-Dist: scikit-learn
Requires-Dist: scipy >=1.4.0
Provides-Extra: all
Requires-Dist: sphinx >=2.0 ; extra == 'all'
Requires-Dist: sphinx-gallery ; extra == 'all'
Requires-Dist: sphinx-rtd-theme ; extra == 'all'
Requires-Dist: mayavi ; extra == 'all'
Requires-Dist: pysurfer ; extra == 'all'
Requires-Dist: numba ; extra == 'all'
Requires-Dist: flake8 ; extra == 'all'
Requires-Dist: coverage ; extra == 'all'
Requires-Dist: pytest >=3.6 ; extra == 'all'
Requires-Dist: pytest-cov ; extra == 'all'
Provides-Extra: doc
Requires-Dist: sphinx >=2.0 ; extra == 'doc'
Requires-Dist: sphinx-gallery ; extra == 'doc'
Requires-Dist: sphinx-rtd-theme ; extra == 'doc'
Provides-Extra: numba
Requires-Dist: numba ; extra == 'numba'
Provides-Extra: plotting
Requires-Dist: mayavi ; extra == 'plotting'
Requires-Dist: pysurfer ; extra == 'plotting'
Provides-Extra: style
Requires-Dist: flake8 ; extra == 'style'
Provides-Extra: test
Requires-Dist: coverage ; extra == 'test'
Requires-Dist: pytest >=3.6 ; extra == 'test'
Requires-Dist: pytest-cov ; extra == 'test'
